memproc/__init__.py
memproc/main.py
memproc/lib/process.py
memproc/lib/process_pool.py
memproc/lib/utils.py
memproc-0.1.2.dist-info/METADATA
memproc-0.1.2.dist-info/WHEEL
memproc-0.1.2.dist-info/entry_points.txt
memproc-0.1.2.dist-info/licenses/LICENSE
memproc-0.1.2.dist-info/RECORD
