Metadata-Version: 2.1
Name: memproc
Version: 0.1.2
Summary: Fancy display of memory usage
Project-URL: homepage, https://github.com/sdelquin/memproc
Project-URL: repository, https://github.com/sdelquin/memproc
Author: Sergio Delgado Quintero
Author-email: sdelquin@gmail.com
Maintainer-email: Sergio Delgado Quintero <sdelquin@gmail.com>
License: MIT License
License-File: LICENSE
Classifier: License :: OSI Approved :: MIT License
Classifier: Operating System :: OS Independent
Classifier: Programming Language :: Python :: 3
Requires-Python: >=3.10
Requires-Dist: psutil==5.9.4
Requires-Dist: rich==12.6.0
Requires-Dist: typer==0.7.0
